README.rst
setup.py
django_pedantic_http_methods.egg-info/PKG-INFO
django_pedantic_http_methods.egg-info/SOURCES.txt
django_pedantic_http_methods.egg-info/dependency_links.txt
django_pedantic_http_methods.egg-info/requires.txt
django_pedantic_http_methods.egg-info/top_level.txt
pedantic_http_methods/__init__.py
pedantic_http_methods/app_settings.py
pedantic_http_methods/models.py