Metadata-Version: 1.0
Name: django-pedantic-http-methods
Version: 1.0.3
Summary: Raises an exception when attempting to perform side effects in GET and HEAD HTTP methods.
Home-page: https://chris-lamb.co.uk/projects/django-pedantic-http-methods
Author: Chris Lamb
Author-email: chris@chris-lamb.co.uk
License: BSD
Platform: UNKNOWN
